sliding_median.cp313-win_amd64.pyd
sliding_median-1.1.0.dist-info/METADATA
sliding_median-1.1.0.dist-info/WHEEL
sliding_median-1.1.0.dist-info/top_level.txt
sliding_median-1.1.0.dist-info/RECORD
