Metadata-Version: 2.4
Name: sliding_median
Version: 1.1.0
Summary: 滑动窗口中位数的高效 C++ 实现（Python 绑定）
Author: Meng Gang
Author-email: 981214502@qq.com
Classifier: Programming Language :: Python :: 3
Classifier: Programming Language :: C++
Classifier: License :: OSI Approved :: MIT License
Classifier: Operating System :: Microsoft :: Windows
Requires-Python: >=3.8
Requires-Dist: pybind11>=2.12.0
Dynamic: author
Dynamic: author-email
Dynamic: classifier
Dynamic: description-content-type
Dynamic: requires-dist
Dynamic: requires-python
Dynamic: summary
